{
    "instaloader": {
        "node_type": "Post",
        "version": "4.4.4"
    },
    "node": {
        "__typename": "GraphVideo",
        "accessibility_caption": null,
        "caption_is_edited": false,
        "clips_music_attribution_info": null,
        "commenting_disabled_for_viewer": false,
        "comments_disabled": false,
        "dash_info": {
            "is_dash_eligible": true,
            "number_of_qualities": 2,
            "video_dash_manifest": "<MPD xmlns=\"urn:mpeg:dash:schema:mpd:2011\" minBufferTime=\"PT1.500S\" type=\"static\" mediaPresentationDuration=\"PT0H0M51.246S\" maxSegmentDuration=\"PT0H0M2.020S\" profiles=\"urn:mpeg:dash:profile:isoff-on-demand:2011,http://dashif.org/guidelines/dash264\">\n <Period duration=\"PT0H0M51.246S\">\n  <AdaptationSet segmentAlignment=\"true\" maxWidth=\"576\" maxHeight=\"720\" maxFrameRate=\"30\" par=\"576:720\" lang=\"und\" subsegmentAlignment=\"true\" subsegmentStartsWithSAP=\"1\">\n   <Representation id=\"18149580568006541vd\" mimeType=\"video/mp4\" codecs=\"avc1.4D401F\" width=\"576\" height=\"720\" frameRate=\"30\" sar=\"1:1\" startWithSAP=\"1\" bandwidth=\"332501\" FBQualityClass=\"sd\" FBQualityLabel=\"576w\" FBPlaybackResolutionMos=\"0:100.00,480:99.28,576:99.08\">\n    <BaseURL>https://scontent-hel2-1.cdninstagram.com/v/t50.2886-16/106509608_149229926751919_7022643700972421365_n.mp4?_nc_ht=scontent-hel2-1.cdninstagram.com&amp;_nc_cat=107&amp;_nc_ohc=oY6JudSBAzEAX9wb1RI&amp;oh=ed77bdd0cbe59624e7fe152bfa7aa0d0&amp;oe=5F034FD5</BaseURL>\n    <SegmentBase indexRangeExact=\"true\" indexRange=\"905-1248\" FBFirstSegmentRange=\"1249-67162\" FBSecondSegmentRange=\"67163-128197\" FBPrefetchSegmentRange=\"1249-128197\">\n      <Initialization range=\"0-904\"/>\n    </SegmentBase>\n   </Representation>\n  <Representation id=\"18149580610006541v\" mimeType=\"video/mp4\" codecs=\"avc1.4D401F\" width=\"258\" height=\"322\" frameRate=\"30\" sar=\"1:1\" startWithSAP=\"1\" bandwidth=\"117976\" FBQualityClass=\"sd\" FBQualityLabel=\"258w\" FBPlaybackResolutionMos=\"0:100.00,480:97.82,576:97.40\">\n    <BaseURL>https://scontent-hel2-1.cdninstagram.com/v/t50.2886-16/106522854_158290155858731_1831293961835609760_n.mp4?_nc_ht=scontent-hel2-1.cdninstagram.com&amp;_nc_cat=111&amp;_nc_ohc=eUIud_VCU1MAX__Y3cu&amp;oh=875eca7015de3af72e5f276d18fa1ddf&amp;oe=5F03005B</BaseURL>\n    <SegmentBase indexRangeExact=\"true\" indexRange=\"907-1250\" FBFirstSegmentRange=\"1251-24410\" FBSecondSegmentRange=\"24411-46790\" FBPrefetchSegmentRange=\"1251-46790\">\n      <Initialization range=\"0-906\"/>\n    </SegmentBase>\n   </Representation>\n  </AdaptationSet>\n <AdaptationSet segmentAlignment=\"true\" lang=\"und\" subsegmentAlignment=\"true\" subsegmentStartsWithSAP=\"1\">\n   <Representation id=\"18149580544006541ad\" mimeType=\"audio/mp4\" codecs=\"mp4a.40.2\" audioSamplingRate=\"44100\" startWithSAP=\"1\" bandwidth=\"66086\">\n    <AudioChannelConfiguration schemeIdUri=\"urn:mpeg:dash:23003:3:audio_channel_configuration:2011\" value=\"2\"/>\n    <BaseURL>https://scontent-hel2-1.cdninstagram.com/v/t50.2886-16/106266337_2848342892059929_6342776998761395457_n.mp4?_nc_ht=scontent-hel2-1.cdninstagram.com&amp;_nc_cat=109&amp;_nc_ohc=_2OIpC3qtPEAX8AhIsT&amp;oh=13bfe6512eefaa0c5c7462207e845ebd&amp;oe=5F030599</BaseURL>\n    <SegmentBase indexRangeExact=\"true\" indexRange=\"866-1209\" FBFirstSegmentRange=\"1210-18596\" FBSecondSegmentRange=\"18597-35068\" FBPrefetchSegmentRange=\"1210-35068\">\n      <Initialization range=\"0-865\"/>\n    </SegmentBase>\n   </Representation>\n  </AdaptationSet>\n </Period>\n</MPD>"
        },
        "dimensions": {
            "height": 800,
            "width": 640
        },
        "display_resources": [
            {
                "config_height": 800,
                "config_width": 640,
                "src": "https://scontent-hel2-1.cdninstagram.com/v/t51.2885-15/e35/106401012_695933251188764_3708068482099041116_n.jpg?_nc_ht=scontent-hel2-1.cdninstagram.com&_nc_cat=108&_nc_ohc=i63fb1N5w2gAX_ePtxl&oh=4671c6a0ffa57d11ef23d466183c3168&oe=5F033B29"
            },
            {
                "config_height": 937,
                "config_width": 750,
                "src": "https://scontent-hel2-1.cdninstagram.com/v/t51.2885-15/e35/106401012_695933251188764_3708068482099041116_n.jpg?_nc_ht=scontent-hel2-1.cdninstagram.com&_nc_cat=108&_nc_ohc=i63fb1N5w2gAX_ePtxl&oh=4671c6a0ffa57d11ef23d466183c3168&oe=5F033B29"
            },
            {
                "config_height": 1350,
                "config_width": 1080,
                "src": "https://scontent-hel2-1.cdninstagram.com/v/t51.2885-15/e35/106401012_695933251188764_3708068482099041116_n.jpg?_nc_ht=scontent-hel2-1.cdninstagram.com&_nc_cat=108&_nc_ohc=i63fb1N5w2gAX_ePtxl&oh=4671c6a0ffa57d11ef23d466183c3168&oe=5F033B29"
            }
        ],
        "display_url": "https://scontent-hel2-1.cdninstagram.com/v/t51.2885-15/e35/106401012_695933251188764_3708068482099041116_n.jpg?_nc_ht=scontent-hel2-1.cdninstagram.com&_nc_cat=108&_nc_ohc=i63fb1N5w2gAX_ePtxl&oh=4671c6a0ffa57d11ef23d466183c3168&oe=5F033B29",
        "edge_liked_by": {
            "count": 35
        },
        "edge_media_preview_comment": {
            "count": 2,
            "edges": [
                {
                    "node": {
                        "created_at": 1593841047,
                        "did_report_as_spam": false,
                        "edge_liked_by": {
                            "count": 0
                        },
                        "id": "17948120014357487",
                        "is_restricted_pending": false,
                        "owner": {
                            "id": "38424405193",
                            "is_verified": false,
                            "profile_pic_url": "https://scontent-hel2-1.cdninstagram.com/v/t51.2885-19/s150x150/104976142_555226735168716_2839993926650004557_n.jpg?_nc_ht=scontent-hel2-1.cdninstagram.com&_nc_ohc=LVP_KJex70sAX-KmLiC&oh=e7b187c140b85744106939855c0eb027&oe=5F28F7F9",
                            "username": "thelimitless_thoughts"
                        },
                        "text": "\ud83d\ude4c\u2764\ufe0f\ud83d\udd25",
                        "viewer_has_liked": false
                    }
                },
                {
                    "node": {
                        "created_at": 1593850355,
                        "did_report_as_spam": false,
                        "edge_liked_by": {
                            "count": 0
                        },
                        "id": "17907110686474995",
                        "is_restricted_pending": false,
                        "owner": {
                            "id": "34704605858",
                            "is_verified": false,
                            "profile_pic_url": "https://scontent-hel2-1.cdninstagram.com/v/t51.2885-19/s150x150/106397184_717828539067469_5579860295190960889_n.jpg?_nc_ht=scontent-hel2-1.cdninstagram.com&_nc_ohc=YGWCQVCzZ_0AX9UjymT&oh=db609a4bc6d782b19a73c27753462b0a&oe=5F2A58A1",
                            "username": "poetry_zzz"
                        },
                        "text": "Woahhh\ud83d\ude0d\u2764\ufe0f",
                        "viewer_has_liked": false
                    }
                }
            ]
        },
        "edge_media_preview_like": {
            "count": 35,
            "edges": []
        },
        "edge_media_to_caption": {
            "edges": [
                {
                    "node": {
                        "text": "\u00d7 \ud83d\ude0a\u2764\ufe0f\n\u2022\n\u2022\n\u2022\n\u2022\n\u2022\nLike  Comment  share \ud83c\udf0d\u2764\ufe0f\n\ud83d\udcaa\ud83d\udc45\"Follow4follow \ud83d\ude0a\n\u2022\n\u2022\n\u2022\n\u2022\n\u2022\nFollow \ud83d\udc49 @ceylon.qoutes for more qoutes to create your own sunshine\ud83c\udf3c\ud83d\udcab\ud83d\ude48\n\u2022\n\u2022\n\u2022\n\u2022\nThink out of the box and relax your mind\ud83c\udf3b\ud83d\udc64\n\n#motivate #inspire #motivation #inspiration #success #love #motivationalquotes #motivational #believe #fitness #quotes #entrepreneur #life #goals #mindset #inspirationalquotes #lifestyle #business #quoteoftheday #motivated #inspirational #positivevibes #instagood #selflove #hustle #positivity #workout #happiness #quote #bhfyp\n\u2022\n\u2022\n\u2022\n\u2764\ufe0fDm for shoutouts\ud83d\udc49 \u270c\ufe0fCheck this out \ud83d\ude48\n@ceylon.qoutes \u2022\n\u2022\n\u2022\n(Srilankan Most popular english thoughts instagram official page \u2764\ufe0f\ud83c\uddf1\ud83c\uddf0)\n\u2022\n\u2022\n\u2022\n\ud83d\udc49Join with us for more features \ud83d\udc64\ud83d\udcab\n\ud83d\udd25Tag us to be featured \ud83c\udf0d\n\u2022\n\u2022\nHave a nice day \ud83c\udf3c"
                    }
                }
            ]
        },
        "edge_media_to_comment": {
            "count": 2
        },
        "edge_media_to_hoisted_comment": {
            "edges": []
        },
        "edge_media_to_parent_comment": {
            "count": 2,
            "edges": [
                {
                    "node": {
                        "created_at": 1593841047,
                        "did_report_as_spam": false,
                        "edge_liked_by": {
                            "count": 0
                        },
                        "edge_threaded_comments": {
                            "count": 0,
                            "edges": [],
                            "page_info": {
                                "end_cursor": null,
                                "has_next_page": false
                            }
                        },
                        "id": "17948120014357487",
                        "is_restricted_pending": false,
                        "owner": {
                            "id": "38424405193",
                            "is_verified": false,
                            "profile_pic_url": "https://scontent-hel2-1.cdninstagram.com/v/t51.2885-19/s150x150/104976142_555226735168716_2839993926650004557_n.jpg?_nc_ht=scontent-hel2-1.cdninstagram.com&_nc_ohc=LVP_KJex70sAX-KmLiC&oh=e7b187c140b85744106939855c0eb027&oe=5F28F7F9",
                            "username": "thelimitless_thoughts"
                        },
                        "text": "\ud83d\ude4c\u2764\ufe0f\ud83d\udd25",
                        "viewer_has_liked": false
                    }
                },
                {
                    "node": {
                        "created_at": 1593850355,
                        "did_report_as_spam": false,
                        "edge_liked_by": {
                            "count": 0
                        },
                        "edge_threaded_comments": {
                            "count": 0,
                            "edges": [],
                            "page_info": {
                                "end_cursor": null,
                                "has_next_page": false
                            }
                        },
                        "id": "17907110686474995",
                        "is_restricted_pending": false,
                        "owner": {
                            "id": "34704605858",
                            "is_verified": false,
                            "profile_pic_url": "https://scontent-hel2-1.cdninstagram.com/v/t51.2885-19/s150x150/106397184_717828539067469_5579860295190960889_n.jpg?_nc_ht=scontent-hel2-1.cdninstagram.com&_nc_ohc=YGWCQVCzZ_0AX9UjymT&oh=db609a4bc6d782b19a73c27753462b0a&oe=5F2A58A1",
                            "username": "poetry_zzz"
                        },
                        "text": "Woahhh\ud83d\ude0d\u2764\ufe0f",
                        "viewer_has_liked": false
                    }
                }
            ],
            "page_info": {
                "end_cursor": null,
                "has_next_page": false
            }
        },
        "edge_media_to_sponsor_user": {
            "edges": []
        },
        "edge_media_to_tagged_user": {
            "edges": [
                {
                    "node": {
                        "user": {
                            "full_name": "Ceylon Qoutes\u00a9 \ud83c\uddf1\ud83c\uddf0",
                            "id": "35077890692",
                            "is_verified": false,
                            "profile_pic_url": "https://scontent-hel2-1.cdninstagram.com/v/t51.2885-19/s150x150/106478074_574367513223859_4603327577385748965_n.jpg?_nc_ht=scontent-hel2-1.cdninstagram.com&_nc_ohc=Sr_R6DAQ_BEAX_UTIxD&oh=a56f78ff2416a74660c14e2e6e4f972f&oe=5F2905C4",
                            "username": "ceylon.qoutes"
                        },
                        "x": 0.0,
                        "y": 0.0
                    }
                }
            ]
        },
        "edge_related_profiles": {
            "edges": []
        },
        "edge_web_media_to_related_media": {
            "edges": []
        },
        "encoding_status": null,
        "fact_check_information": null,
        "fact_check_overall_rating": null,
        "gating_info": null,
        "has_audio": true,
        "has_ranked_comments": false,
        "id": "2345533880857407238",
        "is_ad": false,
        "is_published": true,
        "is_video": true,
        "location": {
            "has_public_page": true,
            "id": 420165945,
            "lat": 6.9184950955,
            "lng": 79.8488862177,
            "name": "Srilankan nature",
            "slug": "srilankan-nature"
        },
        "media_overlay_info": null,
        "media_preview": "ACEqY8UWAjuWIOevJ/xArDIwSPetNim3fuJHXG79NuM1mH3oiaT6CUUUVZkFFFFAy3NBsyR92mLTriczYJ4AHTtnuaanSpV+o5Wb0Guox71FUxNQnirJEopaKAJlheTOxS2KArISrDB9DWrBwgxxwKoXX+uP0rNO7saONlcr55prDuO9Hep4fvr9RVEFbB9DRWvk0UuY05PM/9k=",
        "owner": {
            "blocked_by_viewer": false,
            "edge_followed_by": {
                "count": 1028
            },
            "edge_owner_to_timeline_media": {
                "count": 114
            },
            "followed_by_viewer": false,
            "full_name": "Ceylon Qoutes\u00a9 \ud83c\uddf1\ud83c\uddf0",
            "has_blocked_viewer": false,
            "id": "35077890692",
            "is_private": false,
            "is_unpublished": false,
            "is_verified": false,
            "profile_pic_url": "https://scontent-hel2-1.cdninstagram.com/v/t51.2885-19/s150x150/106478074_574367513223859_4603327577385748965_n.jpg?_nc_ht=scontent-hel2-1.cdninstagram.com&_nc_ohc=Sr_R6DAQ_BEAX_UTIxD&oh=a56f78ff2416a74660c14e2e6e4f972f&oe=5F2905C4",
            "requested_by_viewer": false,
            "restricted_by_viewer": false,
            "username": "ceylon.qoutes"
        },
        "product_type": "feed",
        "sensitivity_friction_info": null,
        "shortcode": "CCNAqMxJi8G",
        "taken_at_timestamp": 1593829486,
        "thumbnail_resources": [
            {
                "config_height": 150,
                "config_width": 150,
                "src": "https://scontent-hel2-1.cdninstagram.com/v/t51.2885-15/e35/c0.72.576.576a/s150x150/106401012_695933251188764_3708068482099041116_n.jpg?_nc_ht=scontent-hel2-1.cdninstagram.com&_nc_cat=108&_nc_ohc=i63fb1N5w2gAX_ePtxl&oh=1dd673c1ec7e4a875cc1973c7e818e9c&oe=5F031CFC"
            },
            {
                "config_height": 240,
                "config_width": 240,
                "src": "https://scontent-hel2-1.cdninstagram.com/v/t51.2885-15/e35/c0.72.576.576a/s240x240/106401012_695933251188764_3708068482099041116_n.jpg?_nc_ht=scontent-hel2-1.cdninstagram.com&_nc_cat=108&_nc_ohc=i63fb1N5w2gAX_ePtxl&oh=eb29ba70ac2cf286a7b2923fc96ff1bb&oe=5F0336FE"
            },
            {
                "config_height": 320,
                "config_width": 320,
                "src": "https://scontent-hel2-1.cdninstagram.com/v/t51.2885-15/e35/c0.72.576.576a/s320x320/106401012_695933251188764_3708068482099041116_n.jpg?_nc_ht=scontent-hel2-1.cdninstagram.com&_nc_cat=108&_nc_ohc=i63fb1N5w2gAX_ePtxl&oh=304db689db04861958c0e40973198fcf&oe=5F02BEC4"
            },
            {
                "config_height": 480,
                "config_width": 480,
                "src": "https://scontent-hel2-1.cdninstagram.com/v/t51.2885-15/e35/c0.72.576.576a/s480x480/106401012_695933251188764_3708068482099041116_n.jpg?_nc_ht=scontent-hel2-1.cdninstagram.com&_nc_cat=108&_nc_ohc=i63fb1N5w2gAX_ePtxl&oh=5fdffe28d6aa2eaccd83bbfda4fe2dd6&oe=5F030105"
            },
            {
                "config_height": 640,
                "config_width": 640,
                "src": "https://scontent-hel2-1.cdninstagram.com/v/t51.2885-15/e35/c0.72.576.576a/106401012_695933251188764_3708068482099041116_n.jpg?_nc_ht=scontent-hel2-1.cdninstagram.com&_nc_cat=108&_nc_ohc=i63fb1N5w2gAX_ePtxl&oh=563d1ce49ab17f902b933ea2f0ea790d&oe=5F02EED2"
            }
        ],
        "thumbnail_src": "https://scontent-hel2-1.cdninstagram.com/v/t51.2885-15/e35/c0.72.576.576a/106401012_695933251188764_3708068482099041116_n.jpg?_nc_ht=scontent-hel2-1.cdninstagram.com&_nc_cat=108&_nc_ohc=i63fb1N5w2gAX_ePtxl&oh=563d1ce49ab17f902b933ea2f0ea790d&oe=5F02EED2",
        "title": "",
        "tracking_token": "eyJ2ZXJzaW9uIjo1LCJwYXlsb2FkIjp7ImlzX2FuYWx5dGljc190cmFja2VkIjp0cnVlLCJ1dWlkIjoiYzBlYTQ2NjZmYTU3NDVhY2JjNzA1M2EzZjUxNDZhMTUyMzQ1NTMzODgwODU3NDA3MjM4Iiwic2VydmVyX3Rva2VuIjoiMTU5Mzg4Mjg1MTM5OXwyMzQ1NTMzODgwODU3NDA3MjM4fDIyNDg4MTU5ODZ8ZjhhM2ZlNWM5ZjhmNTU1NGM3MjNlOWQ4Yjc4ZTUzN2I0Nzk1YWY0ZTA4NWNkMmRjYjQ0NDk5MWE5ZjkxZTA1YyJ9LCJzaWduYXR1cmUiOiIifQ==",
        "video_duration": 51.166,
        "video_play_count": null,
        "video_url": "https://scontent-hel2-1.cdninstagram.com/v/t50.2886-16/106937171_137540434621543_2723069882044715415_n.mp4?_nc_ht=scontent-hel2-1.cdninstagram.com&_nc_cat=107&_nc_ohc=wgbA_U4S7gMAX-Vs0g1&oe=5F02BFE5&oh=d4cfae1d9b3dd054b4ad8fbbed58cb6c",
        "video_view_count": 52,
        "viewer_can_reshare": true,
        "viewer_has_liked": false,
        "viewer_has_saved": false,
        "viewer_has_saved_to_collection": false,
        "viewer_in_photo_of_you": false
    }
}