[
    {
        "id": 17862686233962435,
        "created_at": 1593834608,
        "text": "\ud5ec\uc2a4\uc7a5 \uc88b\uc544\ubcf4\uc778\ub2e4... \uc800\uae30\uac00\uc11c \ud30c\uc6cc\ub9ac\ud504\ud305\ud558\uba74 \uafc0\uc7bc\uc77c\uac70 \uac19\ub2e4...",
        "owner": {
            "id": "1470470716",
            "is_verified": false,
            "profile_pic_url": "https://scontent-hel2-1.cdninstagram.com/v/t51.2885-19/s150x150/20398395_206344353229867_2539817095034568704_a.jpg?_nc_ht=scontent-hel2-1.cdninstagram.com&_nc_ohc=QxeFzn0XA3sAX_i6S3a&oh=6d4a55b68431d7535456469c706eceda&oe=5F2AE361",
            "username": "100kggg"
        },
        "likes_count": 1,
        "answers": [
            {
                "id": 17863340419942359,
                "created_at": 1593834982,
                "text": "@100kggg \ub098\ub3c4 \uc5ec\uae30 \uc8fc\ub9d0\uc5d0\ub9cc \ud83d\ude48",
                "owner": {
                    "id": "1085867",
                    "is_verified": false,
                    "profile_pic_url": "https://scontent-hel2-1.cdninstagram.com/v/t51.2885-19/s150x150/91515784_2895328250581977_7645477193484599296_n.jpg?_nc_ht=scontent-hel2-1.cdninstagram.com&_nc_ohc=EyLGsFbCk9cAX_S-z-1&oh=089f4b8a603d159075c4fa84d8a66ca5&oe=5F2ACB63",
                    "username": "katrin.yunjin"
                },
                "likes_count": 0
            }
        ]
    },
    {
        "id": 17901347191490704,
        "created_at": 1593830551,
        "text": "\uc73c...\ud558\uccb4",
        "owner": {
            "id": "1325304713",
            "is_verified": false,
            "profile_pic_url": "https://scontent-hel2-1.cdninstagram.com/v/t51.2885-19/s150x150/90323074_2521183408172756_8891676973919633408_n.jpg?_nc_ht=scontent-hel2-1.cdninstagram.com&_nc_ohc=AeGeIDssJVIAX8oLI0Q&oh=c0f614c7c47b4774c4c30774c4be6451&oe=5F289242",
            "username": "hj_dailylife"
        },
        "likes_count": 0,
        "answers": [
            {
                "id": 17878587925693611,
                "created_at": 1593831114,
                "text": "@hj_dailylife \uc5ec\uc790\ub294 \ud558\uccb4 \ud83d\ude0d",
                "owner": {
                    "id": "1085867",
                    "is_verified": false,
                    "profile_pic_url": "https://scontent-hel2-1.cdninstagram.com/v/t51.2885-19/s150x150/91515784_2895328250581977_7645477193484599296_n.jpg?_nc_ht=scontent-hel2-1.cdninstagram.com&_nc_ohc=EyLGsFbCk9cAX_S-z-1&oh=089f4b8a603d159075c4fa84d8a66ca5&oe=5F2ACB63",
                    "username": "katrin.yunjin"
                },
                "likes_count": 0
            }
        ]
    }
]